fake_camera/__init__.py
fake_camera/fake_camera.py
fake_camera-0.9.3a0.dist-info/licenses/LICENSE
fake_camera-0.9.3a0.dist-info/METADATA
fake_camera-0.9.3a0.dist-info/WHEEL
fake_camera-0.9.3a0.dist-info/top_level.txt
fake_camera-0.9.3a0.dist-info/RECORD
