Metadata-Version: 2.4
Name: fake-camera
Version: 0.9.3a0
Summary: A Camera Simulator. It creates a moving image in the screen.
Home-page: https://github.com/fjolublar/fake_camera
Download-URL: https://github.com/fjolublar/fake_camera/archive/v0.9.3-alpha.tar.gz
Author: fjolublar
License: MIT
Keywords: Fake Camera,Moving Image,Camera Simulator
Classifier: Development Status :: 3 - Alpha
Classifier: Topic :: Software Development :: Build Tools
Classifier: License :: OSI Approved :: MIT License
Classifier: Programming Language :: Python :: 3.7
License-File: LICENSE
Requires-Dist: Pillow
Requires-Dist: numpy
Dynamic: author
Dynamic: classifier
Dynamic: description
Dynamic: download-url
Dynamic: home-page
Dynamic: keywords
Dynamic: license
Dynamic: license-file
Dynamic: requires-dist
Dynamic: summary
